[{"width":650,"height":526,"Form":"Test All Types List","Description":"This is my form. Please fill it out. It's awesome!","CretedyBy":"User1","AccessedBy":"Admin,User","bicontrols":[{"type":"form-DataTable2","model":{"id":"a61102e7-6410-59d8-1426-de618ceb89a8","controltype":"DataTable2","datatabs":[],"target":"538e31c3-fc16-cab5-c6c0-60823028461c","type":"widget","fieldtype":"Add","table2":{"position":"absolute","width":"750","height":"20px","parenttdwidth":"160px","BorderWidth":"1","class":"table table-bordered","tablename":"test_all_datatypes","colname":"dynamic","formName":"e3225170-97a3-11e7-bdcc-684a9a9df304","ISvalid":"false","select_col":null,"cond_val":"","cond_val2":"","operation":null,"onchange":null,"id":"a61102e7-6410-59d8-1426-de618ceb89a8","SelectEntity":null,"Datasourcetype":null,"selected_text":""}}}]}]